{
    "data": {
        "be3short/HybridSystemsEnvironment": {
            "languages": {
                "nodes": [
                    {
                        "name": "Java"
                    }, 
                    {
                        "name": "TeX"
                    }, 
                    {
                        "name": "CSS"
                    }
                ], 
                "totalCount": 3
            }
        }, 
        "bnestere/nvm_buffer": {
            "languages": {
                "nodes": [
                    {
                        "name": "C"
                    }, 
                    {
                        "name": "Makefile"
                    }
                ], 
                "totalCount": 2
            }
        }, 
        "cruzdb/go-zlog": {
            "languages": {
                "nodes": [
                    {
                        "name": "Go"
                    }, 
                    {
                        "name": "Shell"
                    }
                ], 
                "totalCount": 2
            }
        }, 
        "cruzdb/pg_zlog": {
            "languages": {
                "nodes": [
                    {
                        "name": "C"
                    }, 
                    {
                        "name": "PLpgSQL"
                    }, 
                    {
                        "name": "Makefile"
                    }
                ], 
                "totalCount": 3
            }
        }, 
        "cruzdb/zlog": {
            "languages": {
                "nodes": [
                    {
                        "name": "C++"
                    }, 
                    {
                        "name": "Shell"
                    }, 
                    {
                        "name": "CMake"
                    }, 
                    {
                        "name": "Java"
                    }, 
                    {
                        "name": "Python"
                    }, 
                    {
                        "name": "C"
                    }
                ], 
                "totalCount": 6
            }
        }, 
        "nimble-dev/nimble": {
            "languages": {
                "nodes": [
                    {
                        "name": "C++"
                    }, 
                    {
                        "name": "R"
                    }, 
                    {
                        "name": "Roff"
                    }, 
                    {
                        "name": "C"
                    }, 
                    {
                        "name": "TeX"
                    }, 
                    {
                        "name": "Batchfile"
                    }, 
                    {
                        "name": "Shell"
                    }, 
                    {
                        "name": "M4"
                    }, 
                    {
                        "name": "Makefile"
                    }, 
                    {
                        "name": "CMake"
                    }
                ], 
                "totalCount": 10
            }
        }, 
        "popperized/PopperCI_Toil": {
            "languages": {
                "nodes": [
                    {
                        "name": "Shell"
                    }
                ], 
                "totalCount": 1
            }
        }, 
        "popperized/bams-popper": {
            "languages": {
                "nodes": [
                    {
                        "name": "TeX"
                    }, 
                    {
                        "name": "Jupyter Notebook"
                    }, 
                    {
                        "name": "Python"
                    }, 
                    {
                        "name": "Shell"
                    }
                ], 
                "totalCount": 4
            }
        }, 
        "popperized/cudele-popper": {
            "languages": {
                "nodes": [
                    {
                        "name": "TeX"
                    }, 
                    {
                        "name": "Jupyter Notebook"
                    }, 
                    {
                        "name": "Shell"
                    }, 
                    {
                        "name": "Python"
                    }, 
                    {
                        "name": "Makefile"
                    }
                ], 
                "totalCount": 5
            }
        }, 
        "popperized/lesson-episode-3": {
            "languages": {
                "nodes": [
                    {
                        "name": "Python"
                    }, 
                    {
                        "name": "Shell"
                    }
                ], 
                "totalCount": 2
            }
        }, 
        "popperized/malacology-popper": {
            "languages": {
                "nodes": [
                    {
                        "name": "Roff"
                    }, 
                    {
                        "name": "Jupyter Notebook"
                    }, 
                    {
                        "name": "TeX"
                    }, 
                    {
                        "name": "Lua"
                    }, 
                    {
                        "name": "Shell"
                    }, 
                    {
                        "name": "Makefile"
                    }
                ], 
                "totalCount": 6
            }
        }, 
        "popperized/mantle-popper": {
            "languages": {
                "nodes": [
                    {
                        "name": "HTML"
                    }, 
                    {
                        "name": "Jupyter Notebook"
                    }, 
                    {
                        "name": "TeX"
                    }, 
                    {
                        "name": "Shell"
                    }, 
                    {
                        "name": "Python"
                    }, 
                    {
                        "name": "Lua"
                    }
                ], 
                "totalCount": 6
            }
        }, 
        "popperized/nwp-popper": {
            "languages": {
                "nodes": [
                    {
                        "name": "Shell"
                    }, 
                    {
                        "name": "NCL"
                    }
                ], 
                "totalCount": 2
            }
        }, 
        "popperized/parsplice-popper": {
            "languages": {
                "nodes": [
                    {
                        "name": "Jupyter Notebook"
                    }, 
                    {
                        "name": "Roff"
                    }, 
                    {
                        "name": "TeX"
                    }, 
                    {
                        "name": "Shell"
                    }, 
                    {
                        "name": "Python"
                    }
                ], 
                "totalCount": 5
            }
        }, 
        "popperized/quiho-popper": {
            "languages": {
                "nodes": [
                    {
                        "name": "Jupyter Notebook"
                    }, 
                    {
                        "name": "TeX"
                    }, 
                    {
                        "name": "Shell"
                    }, 
                    {
                        "name": "Python"
                    }
                ], 
                "totalCount": 4
            }
        }, 
        "popperized/zlog-popper": {
            "languages": {
                "nodes": [
                    {
                        "name": "Jupyter Notebook"
                    }, 
                    {
                        "name": "TeX"
                    }, 
                    {
                        "name": "Shell"
                    }, 
                    {
                        "name": "Makefile"
                    }
                ], 
                "totalCount": 4
            }
        }, 
        "systemslab/docker-baseball": {
            "languages": {
                "nodes": [
                    {
                        "name": "Shell"
                    }
                ], 
                "totalCount": 1
            }
        }, 
        "systemslab/docker-cephdev": {
            "languages": {
                "nodes": [
                    {
                        "name": "Shell"
                    }
                ], 
                "totalCount": 1
            }
        }, 
        "systemslab/popper": {
            "languages": {
                "nodes": [
                    {
                        "name": "Go"
                    }, 
                    {
                        "name": "Python"
                    }, 
                    {
                        "name": "Shell"
                    }
                ], 
                "totalCount": 3
            }
        }, 
        "systemslab/tcp_inigo": {
            "languages": {
                "nodes": [
                    {
                        "name": "C"
                    }, 
                    {
                        "name": "Makefile"
                    }
                ], 
                "totalCount": 2
            }
        }, 
        "systemslab/tcp_relentless_inigo": {
            "languages": {
                "nodes": [
                    {
                        "name": "C"
                    }, 
                    {
                        "name": "Makefile"
                    }
                ], 
                "totalCount": 2
            }
        }, 
        "xiszishu/syssim": {
            "languages": {
                "nodes": [
                    {
                        "name": "C++"
                    }, 
                    {
                        "name": "Makefile"
                    }
                ], 
                "totalCount": 2
            }
        }
    }
}